cliopts/__init__.py
cliopts-1.2.0.dist-info/LICENSE
cliopts-1.2.0.dist-info/METADATA
cliopts-1.2.0.dist-info/WHEEL
cliopts-1.2.0.dist-info/top_level.txt
cliopts-1.2.0.dist-info/RECORD
